MANIFEST.in
README.rst
setup.py
mittun/__init__.py
mittun/manage.py
mittun/settings.py
mittun/urls.py
mittun/views.py
mittun.egg-info/PKG-INFO
mittun.egg-info/SOURCES.txt
mittun.egg-info/dependency_links.txt
mittun.egg-info/requires.txt
mittun.egg-info/top_level.txt
mittun/events/__init__.py
mittun/events/admin.py
mittun/events/models.py
mittun/events/management/__init__.py
mittun/events/management/browser_helper.py
mittun/events/management/commands/__init__.py
mittun/events/management/commands/acceptance.py
mittun/events/migrations/0001_initial.py
mittun/events/migrations/0002_auto__add_field_event_name.py
mittun/events/migrations/0003_auto__add_field_event_url.py
mittun/events/migrations/0004_auto__add_field_event_slug.py
mittun/events/migrations/0005_auto__add_field_event_logo.py
mittun/events/migrations/0006_auto__del_field_event_logo.py
mittun/events/migrations/0007_auto__add_location__del_field_event_address__del_field_event_location.py
mittun/events/migrations/0008_auto__add_field_event_logo.py
mittun/events/migrations/0009_auto__del_field_event_url.py
mittun/events/migrations/0010_auto__del_field_event_description__add_field_event_description_en_us__.py
mittun/events/migrations/0011_auto__chg_field_event_description_pt_br__chg_field_event_description_e.py
mittun/events/migrations/0012_auto__del_field_event_logo__del_field_event_date__del_field_event_slug.py
mittun/events/migrations/__init__.py
mittun/registration/__init__.py
mittun/registration/admin.py
mittun/registration/forms.py
mittun/registration/helpers.py
mittun/registration/models.py
mittun/registration/views.py
mittun/registration/migrations/0001_initial.py
mittun/registration/migrations/0002_auto__add_unique_subscriber_email.py
mittun/registration/migrations/__init__.py
mittun/sponsors/__init__.py
mittun/sponsors/admin.py
mittun/sponsors/models.py
mittun/sponsors/urls.py
mittun/sponsors/views.py
mittun/sponsors/migrations/0001_initial.py
mittun/sponsors/migrations/0002_auto__del_field_sponsor_description__add_field_sponsor_description_en_.py
