Metadata-Version: 1.0
Name: mittun
Version: 0.1.2.7
Summary: conference manager
Home-page: UNKNOWN
Author: Flavia Missi
Author-email: flaviamissi@gmail.com
License: UNKNOWN
Platform: UNKNOWN
